abiosgaming/match.py
abiosgaming/exceptions.py
abiosgaming/base_client.py
abiosgaming/utils.py
abiosgaming/__about__.py
abiosgaming/client.py
abiosgaming/__init__.py
abiosgaming.py-0.3.dist-info/METADATA
abiosgaming.py-0.3.dist-info/top_level.txt
abiosgaming.py-0.3.dist-info/WHEEL
abiosgaming.py-0.3.dist-info/metadata.json
abiosgaming.py-0.3.dist-info/RECORD
abiosgaming.py-0.3.dist-info/DESCRIPTION.rst
