Metadata-Version: 2.0
Name: abiosgaming.py
Version: 0.3
Summary: Client for interacting with the AbiosGaming API
Home-page: UNKNOWN
Author: Jeff Dunham
Author-email: jeffrey.a.dunham@gmail.com
License: UNKNOWN
Platform: UNKNOWN
Classifier: Development Status :: 4 - Beta
Classifier: License :: OSI Approved
Classifier: Intended Audience :: Developers
Classifier: Programming Language :: Python
Classifier: Programming Language :: Python :: 2.7
Classifier: Programming Language :: Python :: 3.4
